goerr/__init__.py
goerr/colors.py
goerr/messages.py
goerr/testing.py
goerr/tests.py
goerr-0.11.0.dist-info/LICENSE
goerr-0.11.0.dist-info/METADATA
goerr-0.11.0.dist-info/WHEEL
goerr-0.11.0.dist-info/top_level.txt
goerr-0.11.0.dist-info/RECORD
