Metadata-Version: 2.1
Name: goerr
Version: 0.11.0
Summary: Go style explicit errors handling
Home-page: https://github.com/synw/goerr
Download-URL: https://github.com/synw/goerr/releases/tag/0.11.0
Author: synw
Author-email: synwe@yahoo.com
Keywords: errors,error_handling
Classifier: Development Status :: 4 - Beta
Classifier: Intended Audience :: Developers
Classifier: License :: OSI Approved :: MIT License
Classifier: Programming Language :: Python :: 3.8
License-File: LICENSE
